[
    {
        "minuto": 42,
        "acrescimos": null,
        "tempo": "1º Tempo",
        "tipo": "Goal",
        "detalhe": "Normal Goal",
        "jogador": "Y. En-Nesyri",
        "assistencia": "Y. Attiat-Allah",
        "selecao": {
            "id": 31,
            "nome": "Morocco",
            "escudo": "https://media.api-sports.io/football/teams/31.png"
        }
    },
    {
        "minuto": 51,
        "acrescimos": null,
        "tempo": "2º Tempo",
        "tipo": "subst",
        "detalhe": "Substitution 1",
        "jogador": "Rúben Neves",
        "assistencia": "Cristiano Ronaldo",
        "selecao": {
            "id": 27,
            "nome": "Portugal",
            "escudo": "https://media.api-sports.io/football/teams/27.png"
        }
    },
    {
        "minuto": 51,
        "acrescimos": null,
        "tempo": "2º Tempo",
        "tipo": "subst",
        "detalhe": "Substitution 2",
        "jogador": "Raphaël Guerreiro",
        "assistencia": "João Cancelo",
        "selecao": {
            "id": 27,
            "nome": "Portugal",
            "escudo": "https://media.api-sports.io/football/teams/27.png"
        }
    },
    {
        "minuto": 57,
        "acrescimos": null,
        "tempo": "2º Tempo",
        "tipo": "subst",
        "detalhe": "Substitution 1",
        "jogador": "R. Saïss",
        "assistencia": "A. Dari",
        "selecao": {
            "id": 31,
            "nome": "Morocco",
            "escudo": "https://media.api-sports.io/football/teams/31.png"
        }
    },
    {
        "minuto": 65,
        "acrescimos": null,
        "tempo": "2º Tempo",
        "tipo": "subst",
        "detalhe": "Substitution 2",
        "jogador": "S. Amallah",
        "assistencia": "W. Cheddira",
        "selecao": {
            "id": 31,
            "nome": "Morocco",
            "escudo": "https://media.api-sports.io/football/teams/31.png"
        }
    },
    {
        "minuto": 65,
        "acrescimos": null,
        "tempo": "2º Tempo",
        "tipo": "subst",
        "detalhe": "Substitution 3",
        "jogador": "Y. En-Nesyri",
        "assistencia": "B. Benoun",
        "selecao": {
            "id": 31,
            "nome": "Morocco",
            "escudo": "https://media.api-sports.io/football/teams/31.png"
        }
    },
    {
        "minuto": 69,
        "acrescimos": null,
        "tempo": "2º Tempo",
        "tipo": "subst",
        "detalhe": "Substitution 3",
        "jogador": "Gonçalo Ramos",
        "assistencia": "Rafael Leão",
        "selecao": {
            "id": 27,
            "nome": "Portugal",
            "escudo": "https://media.api-sports.io/football/teams/27.png"
        }
    },
    {
        "minuto": 69,
        "acrescimos": null,
        "tempo": "2º Tempo",
        "tipo": "subst",
        "detalhe": "Substitution 4",
        "jogador": "Otávio",
        "assistencia": "Vitinha",
        "selecao": {
            "id": 27,
            "nome": "Portugal",
            "escudo": "https://media.api-sports.io/football/teams/27.png"
        }
    },
    {
        "minuto": 70,
        "acrescimos": null,
        "tempo": "2º Tempo",
        "tipo": "Card",
        "detalhe": "Yellow Card",
        "jogador": "Achraf Dari",
        "assistencia": null,
        "selecao": {
            "id": 31,
            "nome": "Morocco",
            "escudo": "https://media.api-sports.io/football/teams/31.png"
        }
    },
    {
        "minuto": 79,
        "acrescimos": null,
        "tempo": "2º Tempo",
        "tipo": "subst",
        "detalhe": "Substitution 5",
        "jogador": "Diogo Dalot",
        "assistencia": "Ricardo Horta",
        "selecao": {
            "id": 27,
            "nome": "Portugal",
            "escudo": "https://media.api-sports.io/football/teams/27.png"
        }
    },
    {
        "minuto": 82,
        "acrescimos": null,
        "tempo": "2º Tempo",
        "tipo": "subst",
        "detalhe": "Substitution 4",
        "jogador": "S. Boufal",
        "assistencia": "Y. Jabrane",
        "selecao": {
            "id": 31,
            "nome": "Morocco",
            "escudo": "https://media.api-sports.io/football/teams/31.png"
        }
    },
    {
        "minuto": 82,
        "acrescimos": null,
        "tempo": "2º Tempo",
        "tipo": "subst",
        "detalhe": "Substitution 5",
        "jogador": "H. Ziyech",
        "assistencia": "Z. Aboukhlal",
        "selecao": {
            "id": 31,
            "nome": "Morocco",
            "escudo": "https://media.api-sports.io/football/teams/31.png"
        }
    },
    {
        "minuto": 87,
        "acrescimos": null,
        "tempo": "2º Tempo",
        "tipo": "Card",
        "detalhe": "Yellow Card",
        "jogador": "Vitinha",
        "assistencia": null,
        "selecao": {
            "id": 27,
            "nome": "Portugal",
            "escudo": "https://media.api-sports.io/football/teams/27.png"
        }
    },
    {
        "minuto": 90,
        "acrescimos": 3,
        "tempo": "2º Tempo",
        "tipo": "Card",
        "detalhe": "Yellow Card",
        "jogador": "Walid Cheddira",
        "assistencia": null,
        "selecao": {
            "id": 31,
            "nome": "Morocco",
            "escudo": "https://media.api-sports.io/football/teams/31.png"
        }
    },
    {
        "minuto": 90,
        "acrescimos": 1,
        "tempo": "2º Tempo",
        "tipo": "Card",
        "detalhe": "Yellow Card",
        "jogador": "Walid Cheddira",
        "assistencia": null,
        "selecao": {
            "id": 31,
            "nome": "Morocco",
            "escudo": "https://media.api-sports.io/football/teams/31.png"
        }
    },
    {
        "minuto": 90,
        "acrescimos": 3,
        "tempo": "2º Tempo",
        "tipo": "Card",
        "detalhe": "Red Card",
        "jogador": "Walid Cheddira",
        "assistencia": null,
        "selecao": {
            "id": 31,
            "nome": "Morocco",
            "escudo": "https://media.api-sports.io/football/teams/31.png"
        }
    }
]