{
    "selecao01": {
        "id": 17,
        "nome": "South Korea",
        "escudo": "https://media.api-sports.io/football/teams/17.png",
        "tecnico": "Paulo Bento",
        "formacao": "4-3-3",
        "titulares": [
            {
                "id": 2892,
                "nome": "Kim Seung-Gyu",
                "numeroCamisa": 1,
                "posicao": "G",
                "coordenadas": "1:1"
            },
            {
                "id": 2912,
                "nome": "Kim Moon-Hwan",
                "numeroCamisa": 15,
                "posicao": "D",
                "coordenadas": "2:4"
            },
            {
                "id": 2899,
                "nome": "Kwon Kyung-Won",
                "numeroCamisa": 20,
                "posicao": "D",
                "coordenadas": "2:3"
            },
            {
                "id": 2898,
                "nome": "Kim Young-Gwon",
                "numeroCamisa": 19,
                "posicao": "D",
                "coordenadas": "2:2"
            },
            {
                "id": 2896,
                "nome": "Kim Jin-Su",
                "numeroCamisa": 3,
                "posicao": "D",
                "coordenadas": "2:1"
            },
            {
                "id": 2901,
                "nome": "Hwang In-Beom",
                "numeroCamisa": 6,
                "posicao": "M",
                "coordenadas": "3:3"
            },
            {
                "id": 2903,
                "nome": "Jung Woo-Young",
                "numeroCamisa": 5,
                "posicao": "M",
                "coordenadas": "3:2"
            },
            {
                "id": 927,
                "nome": "Lee Kang-In",
                "numeroCamisa": 18,
                "posicao": "M",
                "coordenadas": "3:1"
            },
            {
                "id": 2906,
                "nome": "Lee Jae-Sung",
                "numeroCamisa": 10,
                "posicao": "F",
                "coordenadas": "4:3"
            },
            {
                "id": 34211,
                "nome": "Cho Gue-Sung",
                "numeroCamisa": 9,
                "posicao": "F",
                "coordenadas": "4:2"
            },
            {
                "id": 186,
                "nome": "Son Heung-Min",
                "numeroCamisa": 7,
                "posicao": "F",
                "coordenadas": "4:1"
            }
        ],
        "reservas": [
            {
                "id": 24888,
                "nome": "Hwang Hee-Chan",
                "numeroCamisa": 11,
                "posicao": "F"
            },
            {
                "id": 34395,
                "nome": "Son Jun-Ho",
                "numeroCamisa": 13,
                "posicao": "M"
            },
            {
                "id": 2910,
                "nome": "Hwang Ui-Jo",
                "numeroCamisa": 16,
                "posicao": "F"
            },
            {
                "id": 34239,
                "nome": "Cho Yu-Min",
                "numeroCamisa": 24,
                "posicao": "D"
            },
            {
                "id": 2897,
                "nome": "Kim Min-Jae",
                "numeroCamisa": 4,
                "posicao": "D"
            },
            {
                "id": 2913,
                "nome": "Kwon Chang-Hoon",
                "numeroCamisa": 22,
                "posicao": "M"
            },
            {
                "id": 34504,
                "nome": "Yoon Jong-Gyu",
                "numeroCamisa": 2,
                "posicao": "D"
            },
            {
                "id": 2894,
                "nome": "Hong Chul",
                "numeroCamisa": 14,
                "posicao": "D"
            },
            {
                "id": 512,
                "nome": "Jeong Woo-Yeong",
                "numeroCamisa": 25,
                "posicao": "M"
            },
            {
                "id": 2890,
                "nome": "Jo Hyeon-Woo",
                "numeroCamisa": 21,
                "posicao": "G"
            },
            {
                "id": 34374,
                "nome": "Song Bum-Keun",
                "numeroCamisa": 12,
                "posicao": "G"
            },
            {
                "id": 2909,
                "nome": "Paik Seung-Ho",
                "numeroCamisa": 8,
                "posicao": "M"
            },
            {
                "id": 34598,
                "nome": "Song Min-Kyu",
                "numeroCamisa": 26,
                "posicao": "F"
            },
            {
                "id": 34417,
                "nome": "Kim Tae-Hwan",
                "numeroCamisa": 23,
                "posicao": "D"
            },
            {
                "id": 2908,
                "nome": "Na Sang-Ho",
                "numeroCamisa": 17,
                "posicao": "F"
            }
        ]
    },
    "selecao02": {
        "id": 27,
        "nome": "Portugal",
        "escudo": "https://media.api-sports.io/football/teams/27.png",
        "tecnico": "Fernando Santos",
        "formacao": "4-3-3",
        "titulares": [
            {
                "id": 369,
                "nome": "Diogo Costa",
                "numeroCamisa": 22,
                "posicao": "G",
                "coordenadas": "1:1"
            },
            {
                "id": 886,
                "nome": "Diogo Dalot",
                "numeroCamisa": 2,
                "posicao": "D",
                "coordenadas": "2:4"
            },
            {
                "id": 373,
                "nome": "Pepe",
                "numeroCamisa": 3,
                "posicao": "D",
                "coordenadas": "2:3"
            },
            {
                "id": 331832,
                "nome": "António Silva",
                "numeroCamisa": 24,
                "posicao": "D",
                "coordenadas": "2:2"
            },
            {
                "id": 855,
                "nome": "João Cancelo",
                "numeroCamisa": 20,
                "posicao": "D",
                "coordenadas": "2:1"
            },
            {
                "id": 41621,
                "nome": "Matheus Nunes",
                "numeroCamisa": 23,
                "posicao": "M",
                "coordenadas": "3:3"
            },
            {
                "id": 2676,
                "nome": "Rúben Neves",
                "numeroCamisa": 18,
                "posicao": "M",
                "coordenadas": "3:2"
            },
            {
                "id": 128384,
                "nome": "Vitinha",
                "numeroCamisa": 16,
                "posicao": "M",
                "coordenadas": "3:1"
            },
            {
                "id": 41103,
                "nome": "Ricardo Horta",
                "numeroCamisa": 21,
                "posicao": "F",
                "coordenadas": "4:3"
            },
            {
                "id": 874,
                "nome": "Cristiano Ronaldo",
                "numeroCamisa": 7,
                "posicao": "F",
                "coordenadas": "4:2"
            },
            {
                "id": 206,
                "nome": "João Mário",
                "numeroCamisa": 17,
                "posicao": "F",
                "coordenadas": "4:1"
            }
        ],
        "reservas": [
            {
                "id": 2063,
                "nome": "André Silva",
                "numeroCamisa": 9,
                "posicao": "F"
            },
            {
                "id": 41104,
                "nome": "João Palhinha",
                "numeroCamisa": 6,
                "posicao": "M"
            },
            {
                "id": 22236,
                "nome": "Rafael Leão",
                "numeroCamisa": 15,
                "posicao": "F"
            },
            {
                "id": 636,
                "nome": "Bernardo Silva",
                "numeroCamisa": 10,
                "posicao": "M"
            },
            {
                "id": 1580,
                "nome": "William Carvalho",
                "numeroCamisa": 14,
                "posicao": "M"
            },
            {
                "id": 41585,
                "nome": "Gonçalo Ramos",
                "numeroCamisa": 26,
                "posicao": "F"
            },
            {
                "id": 583,
                "nome": "João Félix",
                "numeroCamisa": 11,
                "posicao": "F"
            },
            {
                "id": 567,
                "nome": "Rúben Dias",
                "numeroCamisa": 4,
                "posicao": "D"
            },
            {
                "id": 1590,
                "nome": "José Sá",
                "numeroCamisa": 12,
                "posicao": "G"
            },
            {
                "id": 1485,
                "nome": "Bruno Fernandes",
                "numeroCamisa": 8,
                "posicao": "M"
            },
            {
                "id": 2674,
                "nome": "Rui Patrício",
                "numeroCamisa": 1,
                "posicao": "G"
            },
            {
                "id": 8,
                "nome": "Raphaël Guerreiro",
                "numeroCamisa": 5,
                "posicao": "D"
            }
        ]
    }
}